PROCCD-1.0.data/scripts/esst.txt
PROCCD-1.0.data/scripts/fread_db_add
PROCCD-1.0.data/scripts/fread_db_optimise
PROCCD-1.0.data/scripts/multifread
PROCCD-1.0.data/scripts/multifread.orig
PROCCD-1.0.data/scripts/pyfread
prosci/__init__.py
prosci/common.py
prosci/shell.py
prosci/cpp/__init__.py
prosci/cpp/atom2coord.py
prosci/loops/__init__.py
prosci/loops/ccd.py
prosci/loops/esst.py
prosci/loops/fread.py
prosci/loops/freaddb.py
prosci/loops/loopmodel.py
prosci/loops/multifread.py
prosci/util/__init__.py
prosci/util/ali.py
prosci/util/gaps.py
prosci/util/geohash.py
prosci/util/getpdb.py
prosci/util/pdb.py
prosci/util/pdb3d.py
prosci/util/protein.py
prosci/util/residue.py
prosci/util/seq.py
PROCCD-1.0.dist-info/LICENCE
PROCCD-1.0.dist-info/METADATA
PROCCD-1.0.dist-info/WHEEL
PROCCD-1.0.dist-info/top_level.txt
PROCCD-1.0.dist-info/RECORD
